setup.py
MSCTOOLS.egg-info/PKG-INFO
MSCTOOLS.egg-info/SOURCES.txt
MSCTOOLS.egg-info/dependency_links.txt
MSCTOOLS.egg-info/top_level.txt
msctools/__init__.py
msctools/tools.py
msctools/dect/__init__.py
msctools/dect/tools.py