Metadata-Version: 1.0
Name: MSCTOOLS
Version: 0.0.12
Summary: moyan private tools
Home-page: UNKNOWN
Author: moyan
Author-email: ice.moyan@gmail.com
License: UNKNOWN
Platform: UNKNOWN
